LICENSE
README.md
setup.py
ipygee/__init__.py
ipygee/_version.py
ipygee/assets.py
ipygee/chart.py
ipygee/dispatcher.py
ipygee/docs.py
ipygee/eprint.py
ipygee/map.py
ipygee/maptools.py
ipygee/preview.py
ipygee/tasks.py
ipygee/threading.py
ipygee/utils.py
ipygee/widgets.py
ipygee.egg-info/PKG-INFO
ipygee.egg-info/SOURCES.txt
ipygee.egg-info/dependency_links.txt
ipygee.egg-info/requires.txt
ipygee.egg-info/top_level.txt
ipygee/tabs/__init__.py
ipygee/tabs/layers.py