Metadata-Version: 2.1
Name: ipygee
Version: 0.0.18
Summary: A set of tools for working with Google Earth Engine Python API in Jupyter notebooks
Home-page: 
Author: Rodrigo E. Principe
Author-email: fitoprincipe82@gmail.com
License: MIT
Keywords: google earth engine raster image processing gis satelite jupyter notebook ipython
Platform: UNKNOWN
Classifier: Programming Language :: Python :: 2
Classifier: Programming Language :: Python :: 2.7
Classifier: Programming Language :: Python :: 3
Classifier: Programming Language :: Python :: 3.3
Classifier: Programming Language :: Python :: 3.4
Classifier: Programming Language :: Python :: 3.5
Classifier: License :: OSI Approved :: MIT License
Provides-Extra: dev
Provides-Extra: docs
Provides-Extra: testing
License-File: LICENSE
